{
  "render_style": "CUBE",
  "init_modules": [
    "kubejs:swiftshot_velocity",
    "kubejs:enderman_light"
  ],
  "update_modules": [],
  "collision_modules": [
  ],
  "forces": [
    "kubejs:force/point_force/test_point",
    "kubejs:force/vortex/swiftshot_vortex",
    "kubejs:force/drag/test_drag",
    "kubejs:force/gravity/test_gravity",
    "kubejs:force/vector_field/test_vector_field"
  ],
  "render_modules": [
    "kubejs:color/swiftshot_color",
    "kubejs:trail/swiftshot_trail"
  ],
  "face_velocity": true,
  "velocity_stretch_factor": 2.0,
  "should_collide": false
}